pylibsrtp-0.10.0.dist-info/RECORD
pylibsrtp-0.10.0.dist-info/LICENSE
pylibsrtp-0.10.0.dist-info/WHEEL
pylibsrtp-0.10.0.dist-info/top_level.txt
pylibsrtp-0.10.0.dist-info/METADATA
pylibsrtp/_binding.pypy310-pp73-darwin.so
pylibsrtp/__init__.py
pylibsrtp/py.typed
